<?xml version="1.0" encoding="UTF-8"?><database>
    <element label="Lo R M2m Users Cost Centers" max_length="40" name="x_375152_lo_r_m2m_users_cost_centers" sizeclass="0" type="collection">
        <element attributes="encode_utf8=false" label="Cost Center" max_length="32" name="cost_center" reference="cmn_cost_center" type="reference"/>
        <element attributes="encode_utf8=false" label="User" max_length="32" name="user" reference="sys_user" type="reference"/>
        <index name="index">
            <element name="cost_center"/>
        </index>
        <index name="index2">
            <element name="user"/>
        </index>
    </element>
</database>
